tutto_api_client/__init__.py
tutto_api_client/core/endpoints_factory.py
tutto_api_client/helpers/http.py
tutto_api_client/main.py
tutto_api_client/models/authorization.py
tutto_api_client/models/endpoints.py
tutto_api_client/models/entities.py
tutto_api_client/utils/filter_clean_utils.py
tutto_api_client-1.1.1.dist-info/METADATA
tutto_api_client-1.1.1.dist-info/WHEEL
tutto_api_client-1.1.1.dist-info/RECORD
