Metadata-Version: 2.1
Name: tutto-api-client
Version: 1.1.1
Summary: 
Author: rapha-pereira
Author-email: raphaelpgomes1@gmail.com
Requires-Python: >=3.9,<4.0
Classifier: Programming Language :: Python :: 3
Classifier: Programming Language :: Python :: 3.9
Classifier: Programming Language :: Python :: 3.10
Classifier: Programming Language :: Python :: 3.11
Classifier: Programming Language :: Python :: 3.12
Requires-Dist: aiodns (>=3.1.1,<4.0.0)
Requires-Dist: aiohttp (>=3.9.3,<4.0.0)
